py_notify_you/__init__.py
py_notify_you/ntfy.py
py_notify_you/pushbullet.py
py_notify_you-2.0.1.dist-info/LICENSE
py_notify_you-2.0.1.dist-info/METADATA
py_notify_you-2.0.1.dist-info/WHEEL
py_notify_you-2.0.1.dist-info/RECORD
