Metadata-Version: 2.1
Name: Py-Notify-You
Version: 2.0.1
Summary: A simple library for sending notifications
Home-page: https://github.com/shizamuru-dev/PyNotifyYou/
Author: Shizamuru
Requires-Python: >=3.10,<4.0
Classifier: Programming Language :: Python :: 3
Classifier: Programming Language :: Python :: 3.10
Classifier: Programming Language :: Python :: 3.11
Classifier: Programming Language :: Python :: 3.12
Classifier: Programming Language :: Python :: 3.13
Requires-Dist: httpx (>=0.27.2,<0.28.0)
Project-URL: Repository, https://github.com/shizamuru-dev/PyNotifyYou/
